Metadata-Version: 2.4
Name: ssnolib
Version: 2.2.0.3
Summary: SSNOlib is a Python library for working with the Standard Name Ontology (SSNO).
Author-email: Matthias Probst <matthias.probst@kit.edu>
License: MIT
Project-URL: Homepage, https://github.com/matthiasprobst/ssnolib
Project-URL: Repository, https://github.com/matthiasprobst/ssnolib
Project-URL: Issues, https://github.com/matthiasprobst/ssnolib/issues
Keywords: ontology,rdf,semantic-web,standard-names,metadata
Classifier: Programming Language :: Python :: 3.9
Classifier: Programming Language :: Python :: 3.10
Classifier: Programming Language :: Python :: 3.11
Classifier: Programming Language :: Python :: 3.12
Classifier: Programming Language :: Python :: 3.13
Classifier: License :: OSI Approved :: MIT License
Classifier: Operating System :: OS Independent
Classifier: Development Status :: 4 - Beta
Classifier: Topic :: Scientific/Engineering
Requires-Python: <3.14,>3.8
License-File: LICENSE
Requires-Dist: rdflib>=7.0.0
Requires-Dist: appdirs>=1.4.4
Requires-Dist: pydantic[email]<=2.10.6,>=2.7.4
Requires-Dist: python-dateutil>=2.9.0
Requires-Dist: requests>=2.32.4
Requires-Dist: ontolutils<0.28.0,>=0.27.0
Requires-Dist: pint>=0.24.4
Provides-Extra: test
Requires-Dist: pytest>=8.3.2; extra == "test"
Requires-Dist: pytest-cov>=5.0.0; extra == "test"
Requires-Dist: xmltodict>=0.13.0; extra == "test"
Requires-Dist: pypandoc>=1.13; extra == "test"
Provides-Extra: xml
Requires-Dist: xmltodict>=0.13.0; extra == "xml"
Provides-Extra: html
Requires-Dist: pypandoc>=1.13; extra == "html"
Provides-Extra: app
Requires-Dist: Flask>=3.0.3; extra == "app"
Provides-Extra: hdf
Requires-Dist: h5rdmtoolbox; extra == "hdf"
Requires-Dist: streamlit>=1.5.0; extra == "hdf"
Provides-Extra: yaml
Requires-Dist: pyyaml>6.0.0; extra == "yaml"
Provides-Extra: dev
Requires-Dist: ssnolib[app,hdf,html,test,xml,yaml]; extra == "dev"
Provides-Extra: complete
Requires-Dist: ssnolib[app,hdf,html,test,xml,yaml]; extra == "complete"
Dynamic: license-file
